[
  {
    "slug": "atlas-sonore-des-langues-regionales-de-france",
    "title": "Atlas sonore des langues régionales de France",
    "date": "March 2026",
    "year": "2026",
    "ext_url": "https://atlas.lisn.upsaclay.fr/?tab=map",
    "local_img": "media/AtlasLangues.jpg",
    "topics": [
      "Geolocalized recordings",
      "Georeferenced information",
      "Languages",
      "Patrimonial",
      "Sound recordings"
    ],
    "places": [
      "France",
      "World"
    ],
    "tags": [],
    "excerpt": "Une même fable d'Ésope peut être écoutée et lue en français et en langues régionales en cliquant sur les différents points de la carte. On peut retrouver les créoles et de nombreuses langues des Outre-mer, ainsi que les…",
    "body": "<!-- wp:paragraph -->\n<p>Une même fable d'Ésope peut être écoutée et lue en français (en cliquant sur Paris) et en langues régionales (en cliquant sur les différents points de la carte). On peut retrouver les créoles et de nombreuses langues des Outre-mer, ainsi que ce qu'il est convenu d'appeler les langues non-territoriales de France, à partir de la carte du monde (en cliquant dans les rectangles qui leur sont consacrés) ou à partir des onglets correspondants. Les langues non-territoriales illustrées, comme le (r)romani et la langue des signes française (LSF) sont celles envers lesquelles l'État reconnaît avoir une responsabilité patrimoniale. On peut aussi découvrir, dans le voisinage de la France, les langues et dialectes d'Italie, de Belgique, de Suisse, d'Allemagne, de la Péninsule ibérique. On peut enfin accéder à des langues amérindiennes dans des pays tels que la Bolivie.</p>\n<!-- /wp:paragraph -->\n\n<!-- wp:paragraph -->\n<p><em>The same Aesop's fable can be listened to and read in French (by clicking on Paris) and in regional languages (by clicking on the various points on the map). Creoles and many languages from overseas territories can be found, as well as what are commonly called the non-territorial languages of France, accessible from the world map (by clicking in the rectangles dedicated to them) or from the corresponding tabs. The non-territorial languages featured, such as (R)romani and French Sign Language (LSF), are those for which the State acknowledges a patrimonial responsibility. One can also discover, in the vicinity of France, the languages and dialects of Italy, Belgium, Switzerland, Germany, and the Iberian Peninsula. Finally, Amerindian languages can be accessed in countries such as Bolivia.</em></p>\n<!-- /wp:paragraph -->\n\n<!-- wp:image {\"lightbox\":{\"enabled\":false},\"width\":\"300px\",\"sizeSlug\":\"full\",\"linkDestination\":\"custom\",\"align\":\"center\"} -->\n<figure class=\"wp-block-image aligncenter size-full is-resized\"><a href=\"https://atlas.lisn.upsaclay.fr/?tab=map\"><img src=\"media/AtlasLangues.jpg\" alt=\"Atlas sonore des langues régionales de France\" style=\"width:300px\" /></a><figcaption class=\"wp-element-caption\"><a href=\"https://atlas.lisn.upsaclay.fr/?tab=map\">https://atlas.lisn.upsaclay.fr/?tab=map</a></figcaption></figure>\n<!-- /wp:image -->"
  }
]
